tmtool/TmMySQL.py
tmtool/Tools.py
tmtool/__init__.py
tmtool/util.py
tmtoolP-0.1.32.dist-info/LICENSE
tmtoolP-0.1.32.dist-info/METADATA
tmtoolP-0.1.32.dist-info/WHEEL
tmtoolP-0.1.32.dist-info/top_level.txt
tmtoolP-0.1.32.dist-info/RECORD
