Metadata-Version: 2.1
Name: tmtoolP
Version: 0.1.32
Summary: tmtool
Home-page: https://github.com/meihaoyidian/tm-pip-tools
Author: TM-QA
Author-email: vida112728@gmail.com
License: MIT
Platform: UNKNOWN
Classifier: License :: OSI Approved :: MIT License
Classifier: Programming Language :: Python
Classifier: Programming Language :: Python :: 3
Requires-Python: >=3.8.0
Requires-Dist: yagmail
Requires-Dist: faker
Requires-Dist: requests
Requires-Dist: beautifulsoup4
Requires-Dist: pymysql
